README.md
aoc_commons.py
setup.py
./aoc_commons.py
dazbo_aoc_commons.egg-info/PKG-INFO
dazbo_aoc_commons.egg-info/SOURCES.txt
dazbo_aoc_commons.egg-info/dependency_links.txt
dazbo_aoc_commons.egg-info/top_level.txt